{"cameraMode":{"drawMode":0,"name":"Shaded","section":"Shading Mode"},"sceneLighting":true,"audioPlay":false,"sceneViewState":{"m_AlwaysRefresh":false,"showFog":true,"showSkybox":true,"showFlares":true,"showImageEffects":true,"showParticleSystems":true,"showVisualEffectGraphs":true,"m_FxEnabled":true},"in2DMode":false,"pivot":{"x":-1505.5556640625,"y":-1159.0810546875,"z":-142.43528747558595},"rotation":{"x":0.2334667146205902,"y":-0.7063735723495483,"z":0.26945847272872927,"w":0.6116968989372253},"size":1156.1373291015625,"orthographic":true}